{"cameraMode":{"drawMode":0,"name":"Shaded","section":"Shading Mode"},"sceneLighting":false,"audioPlay":false,"sceneViewState":{"m_AlwaysRefresh":false,"showFog":true,"showSkybox":false,"showFlares":true,"showImageEffects":true,"showParticleSystems":true,"showVisualEffectGraphs":true,"m_FxEnabled":true},"in2DMode":false,"pivot":{"x":2240.79345703125,"y":3598.664794921875,"z":-101.46076202392578},"rotation":{"x":0.4016759991645813,"y":0.0767829492688179,"z":-0.033820364624261859,"w":0.911931037902832},"size":0.12094497680664063,"orthographic":true}